setup.py
StandardDistributions/Binomialdistribution.py
StandardDistributions/Gaussiandistribution.py
StandardDistributions/Generaldistribution.py
StandardDistributions/__init__.py
StandardDistributions.egg-info/PKG-INFO
StandardDistributions.egg-info/SOURCES.txt
StandardDistributions.egg-info/dependency_links.txt
StandardDistributions.egg-info/not-zip-safe
StandardDistributions.egg-info/top_level.txt